dolt_utils/__init__.py
dolt_utils/utils.py
dolt_utils-0.1.3.dist-info/METADATA
dolt_utils-0.1.3.dist-info/WHEEL
dolt_utils-0.1.3.dist-info/licenses/LICENSE
dolt_utils-0.1.3.dist-info/RECORD
